ya/__init__.py
ya/dotdict.py
ya.dotdict-1.0.2.dist-info/LICENSE
ya.dotdict-1.0.2.dist-info/METADATA
ya.dotdict-1.0.2.dist-info/WHEEL
ya.dotdict-1.0.2.dist-info/top_level.txt
ya.dotdict-1.0.2.dist-info/RECORD
