Metadata-Version: 2.1
Name: ya.dotdict
Version: 1.0.2
Summary: Attribute access for dictionary-like objects
Home-page: https://github.com/knowikow/ya.dotdict.py
License: UNKNOWN
Platform: UNKNOWN
Classifier: Development Status :: 5 - Production/Stable
Classifier: Intended Audience :: Developers
Classifier: License :: OSI Approved :: MIT License
Classifier: Operating System :: OS Independent
Classifier: Programming Language :: Python :: 3
Classifier: Topic :: Software Development :: Libraries :: Python Modules
Requires-Python: >=3.6
Provides-Extra: dev
Requires-Dist: mutmut ; extra == 'dev'
Provides-Extra: testing
Requires-Dist: pytest ; extra == 'testing'
Requires-Dist: pytest-cov ; extra == 'testing'
Requires-Dist: flake8 ; extra == 'testing'
